vatsal/__init__.py
vatsal/s3_operations.py
vatsal/utils.py
vatsal_test-1.0.7.dist-info/LICENSE
vatsal_test-1.0.7.dist-info/METADATA
vatsal_test-1.0.7.dist-info/WHEEL
vatsal_test-1.0.7.dist-info/top_level.txt
vatsal_test-1.0.7.dist-info/RECORD
